{"siteCatalogProducts": {"siteCatalogProductsResultList": [{"subType": "Trailer", "loadRange": "E", "partNumber": "417491", "productId": "130800", "productLine": "Sport Trail", "productLineId": 0, "type": "SiteCatalogProductItem", "curationType": "", "name": "Sport Trail", "loadSpeedRating": "", "highlight": "", "size": "20.50R8", "gridAttribute": "", "topPicksAttribute": "", "brand": {"image": {"type": "SiteImage", "src": "https://images.simpletire.com/images/manf-logos/13b/carlstar.svg", "altText": "Carlstar", "width": 500, "height": 200}, "label": "Carlstar"}, "link": {"href": "/brands/carlstar-tires/sport-trail#v=1&tireSize=20.5-r-8&mpn=417491&pageSource=sizeCatalog&itemId=130800&curationSource=none&productPos=1", "isExternal": false}, "priceList": [{"label": null, "price": {"estimatedRetailPriceInCents": "15999", "salePriceInCents": "11999"}}], "category": {"name": "", "icon": {"type": "SiteIcon", "svgId": ""}}, "rating": {"value": 4, "quantity": 5}, "siteCatalogPromotionInfo": {"count": 0, "list": []}, "imageList": [{"image": {"type": "SiteImage", "src": "https://images.simpletire.com/images/q_auto/line-images/346/346-sidetread/carlstar-sport-trail.png", "altText": "Tire Sidetread", "width": 800, "height": 800}, "productImageType": "sidetread", "productTypeId": 2, "type": "SiteCatalogProductImage"}, {"image": {"type": "SiteImage", "src": "https://images.simpletire.com/images/q_auto/line-images/346/346-sidewall/carlstar-sport-trail.png", "altText": "Tire Sidewall", "width": 800, "height": 800}, "productImageType": "sidewall", "productTypeId": 2, "type": "SiteCatalogProductImage"}, {"image": {"type": "SiteImage", "src": "https://images.simpletire.com/images/q_auto/line-images/346/346-treadfull/carlstar-sport-trail.png", "altText": "Tire Treadfull", "width": 800, "height": 800}, "productImageType": "treadfull", "productTypeId": 2, "type": "SiteCatalogProductImage"}, {"image": {"type": "SiteImage", "src": "https://images.simpletire.com/images/q_auto/line-images/346/346-treadonly/carlstar-sport-trail.png", "altText": "Tire Treadonly", "width": 800, "height": 800}, "productImageType": "treadonly", "productTypeId": 2, "type": "SiteCatalogProductImage"}], "specList": [{"label": "warranty", "value": "No mileage", "concise": "No mileage warranty", "description": ""}, {"label": "Speed Rating", "value": "", "concise": " speed rating", "description": ""}, {"label": "Load Range", "value": "E", "concise": "E load range", "description": ""}, {"label": "Load Index", "value": "", "concise": " load index", "description": ""}, {"label": "UTQG", "value": "", "concise": " utqg", "description": ""}, {"label": "SideWall", "value": "Blackwall", "concise": "Blackwall sidewall", "description": ""}], "performanceRatingList": [{"label": "Dry", "value": 3.75}, {"label": "Wet", "value": 3.75}, {"label": "Snow", "value": 3.75}, {"label": "Comfort", "value": 4}, {"label": "Noise", "value": 3.75}, {"label": "Treadwear", "value": 3.75}], "activeFilterValueList": [], "deliveryInfo": {"value": "", "origValue": "", "isFeatured": false}, "installTomorrow": null, "dynamicRad": {"originalClass": "", "class": "", "delta": 0, "isUpgrade": false, "isDowngrade": false, "hasLocalDelivery": false, "hasLocalInstall": false, "localInstallerId": null}, "dataMomentList": [], "siteProductLineSizeDetailRoadHazard": null, "installMonday": null, "maxQuantityAllowedForCart": 0, "minQuantityAllowedForCart": 0, "ctaLabel": "", "simpleScore": "7.30", "handlDuraScore": "8.00", "longevityScore": "7.00", "tractionScore": "7.00", "simpleScoreRange": "Good", "handlDuraScoreRange": "Great", "longevityScoreRange": "Good", "tractionScoreRange": "Good", "isDurability": true, "siteProductVisualizationInsightList": [], "customFilterPillPercentOff": null, "volatile": false, "isRunFlat": false, "simpleCrewDiscountInCent": "0", "simpleCrewDiscountType": "$", "productLineScore": null}], "listResultMetadata": {"noExactMatch": false, "pagination": {"total": 1, "resultsPerPage": 35, "offset": 0}}, "siteCatalogProductsMeta": {"title": "20.50r8 tires"}, "siteCatalogFilters": {"filtersList": [{"type": "SiteCatalogFilterList", "header": {"title": "Tire type", "infoLink": null}, "presentationStyle": "Normal", "filterGroups": [{"groupType": "Checklist", "header": {"title": "Vehicle", "infoLink": {"label": "How to choose?", "siteStaticModal": {"type": "SiteStaticModal", "contentId": "catalog-filter-tire-type-vehicle"}}}, "items": [{"title": "Trailer", "flair": null, "description": null, "count": 1, "state": "Normal", "value": {"subtype": "13"}}]}]}, {"type": "SiteCatalogFilterList", "header": {"title": "Brand", "infoLink": null}, "presentationStyle": "Normal", "filterGroups": [{"groupType": "Checklist", "header": {"title": "Featured", "infoLink": null}, "items": [{"title": "Carlstar", "flair": null, "description": null, "count": 1, "state": "Normal", "value": {"brand": "Carlstar"}}]}, {"groupType": "Checklist", "header": {"title": "All", "infoLink": null}, "items": [{"title": "Carlstar", "flair": null, "description": null, "count": 1, "state": "Normal", "value": {"brand": "Carlstar"}}]}]}, {"type": "SiteCatalogFilterRange", "id": "price", "header": {"title": "Price", "infoLink": {"label": "How to choose?", "siteStaticModal": {"type": "SiteStaticModal", "contentId": "catalog-filter-price-range"}}}, "unit": "UnitUSD", "minValue": 119, "maxValue": 120, "step": 1, "currentMinValue": null, "currentMaxValue": null}, {"type": "SiteCatalogFilterRange", "id": "simpleScore", "header": {"title": "Score", "infoLink": {"label": "How to choose?", "siteStaticModal": {"type": "SiteStaticModal", "contentId": "catalog-filter-simple-score"}}}, "unit": null, "minValue": 7, "maxValue": 10, "step": 0.1, "currentMinValue": 0, "currentMaxValue": 0}, {"type": "SiteCatalogFilterList", "header": {"title": "More filters", "infoLink": null}, "presentationStyle": "Large", "filterGroups": [{"groupType": "Checklist", "header": {"title": "Popular Filters", "infoLink": null}, "items": [{"title": "Show tires with deals", "flair": null, "description": null, "count": 0, "state": "Disabled", "value": {"deals": "true"}}]}, {"groupType": "Checklist", "header": {"title": "Sidewall types", "infoLink": null}, "items": [{"title": "Blackwall", "flair": null, "description": null, "count": 1, "state": "Normal", "value": {"sidewall": "BW"}}]}, {"groupType": "Radio", "header": {"title": "Run flat", "infoLink": null}, "items": null}, {"groupType": "Radio", "header": {"title": "Studded/Studdable", "infoLink": null}, "items": [{"title": "Show only studded", "flair": null, "description": "", "count": 0, "state": "Disabled", "value": {"studs": "studded"}}, {"title": "Show only studdable", "flair": null, "description": "", "count": 0, "state": "Disabled", "value": {"studs": "studdable"}}, {"title": "Show both studded and studdable", "flair": null, "description": "", "count": 0, "state": "Disabled", "value": {"studs": "studded,studdable"}}, {"title": "Include studded and studdable", "flair": null, "description": "", "count": 1, "state": "Selected", "value": {"studs": ""}}]}, {"groupType": "Radio", "header": {"title": "Three-Peak Mountain Snowflake", "infoLink": null}, "items": [{"title": "Show only 3PMS", "flair": null, "description": "", "count": 0, "state": "Disabled", "value": {"threePms": "true"}}, {"title": "Do not show 3PMS", "flair": null, "description": "", "count": 1, "state": "Normal", "value": {"threePms": "false"}}, {"title": "Include 3PMS", "flair": null, "description": "", "count": 1, "state": "Selected", "value": {"threePms": ""}}]}]}], "sortList": [{"title": "Recommended", "description": "Fastest delivery, best ratings and value", "state": "Selected", "value": {"sort": "bestMatch", "order": null}}, {"title": "Low to High", "description": "", "state": "Normal", "value": {"sort": "price", "order": "asc"}}, {"title": "High to Low", "description": "", "state": "Normal", "value": {"sort": "price", "order": "desc"}}], "totalMatches": 1}, "headerShopInfo": {"localShopsCount": 0, "carLogo": null, "pricePerTireInCents": 0, "isTiresInstallable": false}, "dominantSubType": 13, "brandTier": null}, "customer_type": "Retail", "nonInstallable": true}